powerset_calibration/__init__.py
powerset_calibration/evaluation.py
powerset_calibration/inference.py
powerset_calibration/protocol.py
powerset_calibration/region_selector.py
powerset_calibration/pipelines/__init__.py
powerset_calibration/pipelines/soft_segmentation.py
powerset_calibration/utils/__init__.py
powerset_calibration/utils/inference.py
powerset_calibration/utils/permutation.py
powerset_calibration/utils/pyannote_core.py
powerset_calibration/utils/torch.py
powerset_calibration-0.1.3.dist-info/WHEEL
powerset_calibration-0.1.3.dist-info/METADATA
powerset_calibration-0.1.3.dist-info/RECORD
