Metadata-Version: 2.1
Name: powerset_calibration
Version: 0.1.3
Summary: Companion package to the 'On the calibration of powerset speaker diarization models' paper published at Interspeech 2024.
Author-email: Alexis Plaquet <alexis.plaquet@irit.fr>
Requires-Python: >=3.8.1
Classifier: Development Status :: 3 - Alpha
Classifier: Intended Audience :: Developers
Classifier: License :: OSI Approved :: MIT License
Classifier: Programming Language :: Python :: 3 :: Only
Classifier: Programming Language :: Python :: 3.8
Classifier: Programming Language :: Python :: 3.9
Classifier: Programming Language :: Python :: 3.10
Classifier: Programming Language :: Python :: 3.11
Requires-Dist: pyannote-audio >= 3.1
Requires-Dist: pandas
Requires-Dist: tqdm
Requires-Dist: pyarrow
Project-URL: Documentation, https://frenchkrab.github.io/powerset_calibration
Project-URL: Source, https://github.com/FrenchKrab/powerset_calibration
Project-URL: Tracker, https://github.com/FrenchKrab/powerset_calibration/issues
